src/__init__.py
src/__main__.py
src/main.py
greet_girl-1.0.0.dist-info/LICENSE
greet_girl-1.0.0.dist-info/METADATA
greet_girl-1.0.0.dist-info/WHEEL
greet_girl-1.0.0.dist-info/entry_points.txt
greet_girl-1.0.0.dist-info/top_level.txt
greet_girl-1.0.0.dist-info/RECORD
