Metadata-Version: 2.1
Name: greet-girl
Version: 1.0.0
Summary: Time of greeting girl on WeChat
Home-page: https://github.com/itswcg/Greet-girlfriend
Author: itswcg
Author-email: itswcg@gmail.com
License: UNKNOWN
Platform: UNKNOWN
Classifier: Programming Language :: Python :: 3
Classifier: License :: OSI Approved :: MIT License
Classifier: Operating System :: OS Independent
Requires-Dist: APScheduler (==3.5.3)
Requires-Dist: itchat (==1.3.10)
